{"informationCenter":[{"ColumnName":"Destination and fares","Links":[{"Label":"Jetstar destinations","URL":"http:\/\/www.jetstar.com\/au\/en\/destinations","Updated":"False"},{"Label":"Flex","URL":"http:\/\/www.jetstar.com\/au\/en\/flexibiz","Updated":"False"},{"Label":"Fares and bundles","URL":"http:\/\/www.jetstar.com\/au\/en\/help\/articles\/economy-bundles-whats-included","Updated":"False"},{"Label":"Hotels","URL":"http:\/\/www.jetstar.com\/au\/en\/hotels","Updated":"False"},{"Label":"About Jetstar","URL":"http:\/\/www.jetstar.com\/au\/en\/about-us","Updated":"False"}]},{"ColumnName":"Check-in and booking","Links":[{"Label":"Web check-in","URL":"https:\/\/book.jetstar.com\/retrievebooking.aspx?action=showcheckin&culture=en-ca","Updated":"False"},{"Label":"Manage booking","URL":"https:\/\/booknow.jetstar.com\/login.aspx?culture=en-AU","Updated":"False"},{"Label":"Jetstar app","URL":"http:\/\/www.jetstar.com\/au\/en\/jetstar-app","Updated":"False"}]},{"ColumnName":"News and contact","Links":[{"Label":"Travel advice","URL":"http:\/\/www.jetstar.com\/au\/en\/help\/articles\/travel-advice","Updated":"False"}]}],"footer":[{"Label":"Contact us","URL":"http:\/\/www.jetstar.com"},{"Label":"Customer Guarantee","URL":"http:\/\/www.jetstar.com"},{"Label":"Privacy policy","URL":"http:\/\/www.jetstar.com"},{"Label":"Website Terms of use","URL":"http:\/\/www.jetstar.com"},{"Label":"Terms & Conditions of Carriage","URL":"http:\/\/www.jetstar.com"}],"banners":[{"Name":"VIDEO","Image":"\/\/www.jetstar.com\/au\/en\/businessagentinfo\/\/~\/_media\/Tradesite\/Banners\/20191118_7kgTable-01.png?bc=White","Caption":"","URL":""}]}